bdtr/__init__.py
bdtr/__main__.py
bdtr/bdtr.py
bdtr/bdtr_list.py
bdtr/get_baiduid_token.py
bdtr/get_bd_token_baiduid.py
bdtr/js2py_sign.py
bdtr/py_sign.py
baidu_tr_free-0.0.10.dist-info/LICENSE.txt
baidu_tr_free-0.0.10.dist-info/METADATA
baidu_tr_free-0.0.10.dist-info/WHEEL
baidu_tr_free-0.0.10.dist-info/top_level.txt
baidu_tr_free-0.0.10.dist-info/RECORD
