Metadata-Version: 2.1
Name: baidu-tr-free
Version: 0.0.10
Summary: baidu translate for free
Home-page: http://github.com/ffreemt/baidu-tr-free
Author: mikeee
License: MIT License
Download-URL: https://github.com/ffreemt/baidu-tr-free/archive/v_0.0.10.tar.gz
Keywords: machine translation,free,scraping
Platform: UNKNOWN
Classifier: Development Status :: 3 - Alpha
Classifier: Intended Audience :: Developers
Classifier: Programming Language :: Python :: 3
Classifier: Programming Language :: Python :: 3.5
Classifier: Programming Language :: Python :: 3.6
Classifier: License :: OSI Approved :: MIT License
Requires-Dist: requests-cache
Requires-Dist: js2py
Requires-Dist: jsonpath-rw
Requires-Dist: tqdm
Requires-Dist: httpx
Requires-Dist: requests
Requires-Dist: browser-cookie3 (>=0.10.1)
Requires-Dist: jmespath
Requires-Dist: loguru
Requires-Dist: pyquery
